wltr_functions/__init__.py
wltr_functions/cleansing.py
wltr_functions/databases.py
wltr_functions/deltalake.py
wltr_functions/integrations.py
wltr_functions/secrets.py
wltr_functions-3.3.3.dist-info/LICENSE
wltr_functions-3.3.3.dist-info/METADATA
wltr_functions-3.3.3.dist-info/WHEEL
wltr_functions-3.3.3.dist-info/top_level.txt
wltr_functions-3.3.3.dist-info/RECORD
