Metadata-Version: 2.1
Name: wltr-functions
Version: 3.3.3
Summary: WLTR Functions
Home-page: https://github.com/walteravelino/wltr-functions
Author: Walter José Avelino da Silva
Author-email: walter.avelin@gmail.com
License: UNKNOWN
Platform: UNKNOWN
Classifier: Programming Language :: Python :: 3
Classifier: License :: OSI Approved :: MIT License
Classifier: Operating System :: OS Independent
License-File: LICENSE
Requires-Dist: boto3
Requires-Dist: botocore
Requires-Dist: simple-salesforce
Requires-Dist: email-validator
Requires-Dist: cx-Oracle
Requires-Dist: pymongo
Requires-Dist: pycryptodomex
Requires-Dist: psycopg2-binary
Requires-Dist: JayDeBeApi
